geodata2pg/__init__.py
geodata2pg/__version__.py
geodata_to_pgsql/__init__.py
geodata_to_pgsql/__version__.py
geodata2pg-0.1.0.dist-info/LICENSE
geodata2pg-0.1.0.dist-info/METADATA
geodata2pg-0.1.0.dist-info/WHEEL
geodata2pg-0.1.0.dist-info/top_level.txt
geodata2pg-0.1.0.dist-info/RECORD
