Metadata-Version: 2.1
Name: geodata2pg
Version: 0.1.0
Summary: 🐰 批量导入 geojson shpfile 到 postgresql
Home-page: https://github.com/zhuqiandai/geodata2pg
Author: wangzhx
Author-email: w1132154046@outlook.com
License: MIT
Platform: UNKNOWN
Classifier: License :: OSI Approved :: MIT License
Classifier: Programming Language :: Python
Classifier: Programming Language :: Python :: 3
Classifier: Programming Language :: Python :: 3.6
Classifier: Programming Language :: Python :: Implementation :: CPython
Classifier: Programming Language :: Python :: Implementation :: PyPy
Requires-Python: >=3.6.0
License-File: LICENSE
Requires-Dist: geopandas
Requires-Dist: sqlalchemy
Requires-Dist: psycopg2-binary
Requires-Dist: geoalchemy2
